disckit/__init__.py
disckit/config.py
disckit/errors.py
disckit/cogs/__init__.py
disckit/cogs/loader.py
disckit/cogs/commands/help.py
disckit/cogs/worker/__init__.py
disckit/cogs/worker/error_handler.py
disckit/cogs/worker/owner_id_handler.py
disckit/cogs/worker/status_handler.py
disckit/utils/__init__.py
disckit/utils/cooldown.py
disckit/utils/embeds.py
disckit/utils/mention_tree.py
disckit/utils/paginator.py
disckit/utils/ui.py
disckit-1.1.4.dist-info/licenses/LICENSE
disckit-1.1.4.dist-info/METADATA
disckit-1.1.4.dist-info/WHEEL
disckit-1.1.4.dist-info/top_level.txt
disckit-1.1.4.dist-info/RECORD
