Metadata-Version: 2.4
Name: disckit
Version: 1.1.4
Summary: An open source utilities library for the disutils bots.
Author-email: Jiggly Balls <jigglyballs9000@gmail.com>
License-Expression: MIT
Project-URL: Homepage, https://github.com/disutils/disckit
Project-URL: Issues, https://github.com/disutils/disckit/issues
Classifier: Development Status :: 5 - Production/Stable
Classifier: Natural Language :: English
Classifier: Operating System :: MacOS
Classifier: Operating System :: Microsoft :: Windows
Classifier: Operating System :: POSIX
Classifier: Operating System :: Unix
Classifier: Programming Language :: Python
Classifier: Programming Language :: Python :: 3
Classifier: Programming Language :: Python :: 3.11
Classifier: Programming Language :: Python :: 3.12
Classifier: Programming Language :: Python :: 3.13
Classifier: Topic :: Software Development :: Libraries
Classifier: Topic :: Utilities
Classifier: Typing :: Typed
Requires-Python: >=3.11
License-File: LICENSE
Requires-Dist: discord-py>=2.5.0
Requires-Dist: typing-extensions>=4.13.2
Dynamic: license-file
